setup.py
yxspkg_required.py
yxs_required.egg-info/PKG-INFO
yxs_required.egg-info/SOURCES.txt
yxs_required.egg-info/dependency_links.txt
yxs_required.egg-info/requires.txt
yxs_required.egg-info/top_level.txt